npvcc2016/PyTorch/Lightning/__init__.py
npvcc2016/PyTorch/Lightning/datamodule/__init__.py
npvcc2016/PyTorch/Lightning/datamodule/spectrogram.py
npvcc2016/PyTorch/Lightning/datamodule/waveform.py
npvcc2016/PyTorch/__init__.py
npvcc2016/PyTorch/dataset/__init__.py
npvcc2016/PyTorch/dataset/spectrogram.py
npvcc2016/PyTorch/dataset/waveform.py
npvcc2016/__init__.py
npvcc2016/corpus.py
npvcc2016/fs.py
npvcc2016-3.0.0.dist-info/LICENSE
npvcc2016-3.0.0.dist-info/WHEEL
npvcc2016-3.0.0.dist-info/METADATA
npvcc2016-3.0.0.dist-info/RECORD
