Metadata-Version: 2.1
Name: npvcc2016
Version: 3.0.0
Summary: npvcc2016: Python loader of npVCC2016 speech corpus
Home-page: https://github.com/tarepan/npVCC2016
License: MIT
Author: Tarepan
Requires-Python: >=3.6.1,<4.0.0
Classifier: License :: OSI Approved :: MIT License
Classifier: Programming Language :: Python :: 3
Classifier: Programming Language :: Python :: 3.7
Classifier: Programming Language :: Python :: 3.8
Classifier: Programming Language :: Python :: 3.9
Requires-Dist: fsspec[s3] (>=0.8.4,<0.9.0)
Requires-Dist: pytorch-lightning (>=1.0.6,<2.0.0)
Requires-Dist: torch
Requires-Dist: torchaudio (>=0.7.0,<0.8.0)
Project-URL: Repository, https://github.com/tarepan/npVCC2016
